mcp_quantdata/__init__.py
mcp_quantdata/mcp_tools.py
mcp_quantdata-20260115.dist-info/METADATA
mcp_quantdata-20260115.dist-info/WHEEL
mcp_quantdata-20260115.dist-info/entry_points.txt
mcp_quantdata-20260115.dist-info/RECORD
