Metadata-Version: 2.4
Name: mcp-quantdata
Version: 20260115
Summary: MCP 量化数据工具
Author-email: vex1023 <vex1023@qq.com>
Requires-Python: >=3.13
Requires-Dist: mcp[cli]>=1.25.0
Requires-Dist: polars>=1.37.1
Requires-Dist: vxsched>=20260104
Requires-Dist: vxutils>=20260114
